web_encoder/__init__.py
web_encoder/__main__.py
web_encoder/exceptions.py
web_encoder/main.py
Web_Encoder-0.1.2.dist-info/LICENSE
Web_Encoder-0.1.2.dist-info/METADATA
Web_Encoder-0.1.2.dist-info/WHEEL
Web_Encoder-0.1.2.dist-info/top_level.txt
Web_Encoder-0.1.2.dist-info/RECORD
