Metadata-Version: 2.1
Name: Web-Encoder
Version: 0.1.2
Summary: Used to encode or decode data in a web-friendly format.
Home-page: https://github.com/cesarmerjan/web_encoder
Download-URL: https://github.com/cesarmerjan/web_encoder/archive/refs/heads/master.zip
Author: Cesar Merjan
Author-email: cesarmerjan@gmail.com
License: MIT
Keywords: encode,backend,session
Platform: UNKNOWN
Classifier: Development Status :: 4 - Beta
Classifier: License :: OSI Approved :: Apache Software License
Classifier: Intended Audience :: Developers
Classifier: Environment :: Web Environment
Classifier: Topic :: Utilities
Classifier: Topic :: Software Development
Classifier: Topic :: Software Development :: Libraries
Classifier: Topic :: Software Development :: Pre-processors
Classifier: Programming Language :: Python :: 3
Classifier: Programming Language :: Python :: 3 :: Only
Classifier: Programming Language :: Python :: 3.6
Classifier: Programming Language :: Python :: 3.7
Classifier: Programming Language :: Python :: 3.8
Classifier: Operating System :: Unix
Classifier: Operating System :: MacOS :: MacOS X
Classifier: Operating System :: Microsoft :: Windows
Requires-Python: >3.6
License-File: LICENSE
